searchit/__init__.py
searchit/exceptions/__init__.py
searchit/scrapers/__init__.py
searchit/scrapers/bing.py
searchit/scrapers/google.py
searchit/scrapers/qwant.py
searchit/scrapers/scraper.py
searchit/scrapers/yandex.py
searchit-2019.12.30.2.dist-info/LICENSE
searchit-2019.12.30.2.dist-info/METADATA
searchit-2019.12.30.2.dist-info/WHEEL
searchit-2019.12.30.2.dist-info/top_level.txt
searchit-2019.12.30.2.dist-info/RECORD
