Metadata-Version: 2.1
Name: searchit
Version: 2019.12.30.2
Summary: Aysncio search engine scraping package
Home-page: https://github.com/EdmundMartin/search_it
Author: Edmund Martin
Maintainer: Edmund Martin <edmartin101@gmail.com>
Maintainer-email: edmartin101@gmail.com
License: UNKNOWN
Platform: UNKNOWN
Classifier: Intended Audience :: Developers
Classifier: Programming Language :: Python
Classifier: Programming Language :: Python :: 3
Classifier: Programming Language :: Python :: 3.6
Classifier: Programming Language :: Python :: 3.7
Classifier: Operating System :: POSIX
Classifier: Operating System :: MacOS :: MacOS X
Classifier: Operating System :: Microsoft :: Windows
Requires-Python: >=3.6
